<?xml version="1.0" encoding="UTF-8"?>
<metadata xml:lang="en"><Esri><CreaDate>20120423</CreaDate><CreaTime>09361100</CreaTime><ArcGISFormat>1.0</ArcGISFormat><SyncOnce>TRUE</SyncOnce><DataProperties><itemProps><itemLocation><linkage Sync="TRUE">file://\\AKC1SD1178-MZ10\D$\data\WP51TEXT\WCGFISH\SEDDATA\AI\AI2012\AI_Regions_Poly</linkage><protocol Sync="TRUE">Local Area Network</protocol></itemLocation></itemProps><copyHistory><copy source="D:\data\WP51TEXT\WCGFISH\SEDDATA\AI\AI2010\AI_Regions_Poly" dest="\\AKC1SD1178-MZ10\D$\data\WP51TEXT\WCGFISH\SEDDATA\AI\AI2012\AI_Regions_Poly" date="20120423" time="09361100"></copy></copyHistory></DataProperties></Esri></metadata>
